README.rst
setup.py
tdlc_connector/__init__.py
tdlc_connector/api.py
tdlc_connector/connections.py
tdlc_connector/constants.py
tdlc_connector/cursors.py
tdlc_connector/exceptions.py
tdlc_connector/formats.py
tdlc_connector/results.py
tdlc_connector/version.py
tencentcloud_dlc_connector.egg-info/PKG-INFO
tencentcloud_dlc_connector.egg-info/SOURCES.txt
tencentcloud_dlc_connector.egg-info/dependency_links.txt
tencentcloud_dlc_connector.egg-info/requires.txt
tencentcloud_dlc_connector.egg-info/top_level.txt