Metadata-Version: 1.2
Name: tencentcloud-dlc-connector
Version: 1.4.0
Summary: Tencentcloud DLC connector, connect to DLC engines using SQL.
Home-page: UNKNOWN
Author: Tencentcloud DLC Team.
Maintainer-email: dlc@tencent.com
License: Apache License Version 2.0
Platform: any
Classifier: Development Status :: 5 - Production/Stable
Classifier: Intended Audience :: Developers
Classifier: License :: OSI Approved :: Apache Software License
Classifier: Programming Language :: Python
Classifier: Programming Language :: Python :: 3
Classifier: Programming Language :: Python :: 3.9
